gemini_calo/__init__.py
gemini_calo/__main__.py
gemini_calo/config.py
gemini_calo/logger.py
gemini_calo/middlewares/__init__.py
gemini_calo/middlewares/auth.py
gemini_calo/middlewares/logging.py
gemini_calo/middlewares/model_override.py
gemini_calo/middlewares/rollup.py
gemini_calo/proxy.py
gemini_calo-0.1.4.dist-info/METADATA
gemini_calo-0.1.4.dist-info/WHEEL
gemini_calo-0.1.4.dist-info/entry_points.txt
gemini_calo-0.1.4.dist-info/RECORD
