Metadata-Version: 2.4
Name: gemini-calo
Version: 0.1.4
Summary: A Fastapi Based Proxy for Gemini API
License: AGPL-3.0-or-later
Author: Go Frendi Gunawan
Author-email: gofrendiasgard@gmail.com
Requires-Python: >=3.10,<4.0.0
Classifier: License :: OSI Approved :: GNU Affero General Public License v3 or later (AGPLv3+)
Classifier: Programming Language :: Python :: 3
Classifier: Programming Language :: Python :: 3.10
Classifier: Programming Language :: Python :: 3.11
Classifier: Programming Language :: Python :: 3.12
Classifier: Programming Language :: Python :: 3.13
Classifier: Programming Language :: Python :: 3.14
Requires-Dist: cachetools (>=6.1.0,<7.0.0)
Requires-Dist: fastapi (>=0.116.1)
Requires-Dist: uvicorn (>=0.35.0)
Project-URL: Documentation, https://github.com/state-alchemists/gemini-calo
Project-URL: Homepage, https://github.com/state-alchemists/gemini-calo
Project-URL: Repository, https://github.com/state-alchemists/gemini-calo
